hyperstools/__init__.py
hyperstools/crontab.py
hyperstools/lib.py
hyperstools/s3.py
hyperstools/sftp.py
hyperstools/ssh.py
hyperstools/mq/__init__.py
hyperstools/mq/asyncTask.py
hyperstools/mq/consumer.py
hyperstools/mq/lib.py
hyperstools/mq/publisher.py
tests/__init__.py
tests/test_hyperstools.py
tests/test_mq.py
tests/test_ssh.py
hyperstools-0.1.34.dist-info/AUTHORS.rst
hyperstools-0.1.34.dist-info/METADATA
hyperstools-0.1.34.dist-info/WHEEL
hyperstools-0.1.34.dist-info/top_level.txt
hyperstools-0.1.34.dist-info/RECORD
