Metadata-Version: 2.1
Name: hyperstools
Version: 0.1.34
Summary: Python Boilerplate contains all the boilerplate you need to create a Python package.
Home-page: https://github.com/drinksober/hyperstools
Author: hypersTools
Author-email: drinks.huang@hypers.com
License: UNKNOWN
Keywords: hyperstools
Platform: UNKNOWN
Classifier: Development Status :: 2 - Pre-Alpha
Classifier: Intended Audience :: Developers
Classifier: Natural Language :: English
Classifier: Programming Language :: Python :: 2
Classifier: Programming Language :: Python :: 2.7
Classifier: Programming Language :: Python :: 3
Classifier: Programming Language :: Python :: 3.4
Classifier: Programming Language :: Python :: 3.5
Classifier: Programming Language :: Python :: 3.6
Classifier: Programming Language :: Python :: 3.7
Requires-Dist: boto3
Requires-Dist: pika (>=1.0.0)
Requires-Dist: paramiko
Requires-Dist: apscheduler
